py_img_editor/__init__.py
py_img_editor/index.py
py_img_editor/uwsgi.ini
py_img_editor-0.0.2.dist-info/METADATA
py_img_editor-0.0.2.dist-info/WHEEL
py_img_editor-0.0.2.dist-info/entry_points.txt
py_img_editor-0.0.2.dist-info/top_level.txt
py_img_editor-0.0.2.dist-info/RECORD
