Metadata-Version: 2.1
Name: py-img-editor
Version: 0.0.2
Summary: Image editor using Python, uWSGI, and Pillow
Home-page: https://github.com/kimballo/py-img-editor
Author: Kimball Leavitt
Author-email: kimballleavitt@gmail.com
License: UNKNOWN
Platform: UNKNOWN
Classifier: Programming Language :: Python :: 3
Classifier: License :: OSI Approved :: MIT License
Requires-Dist: Pillow (==5.3.0)
